{
  "generator-jhipster": {
    "authenticationType": "jwt",
    "clientFramework": "angularX",
    "serverPort": "8080",
    "serviceDiscoveryType": "eureka",
    "skipUserManagement": false,
    "withAdminUi": true,
    "baseName": "myTrackit",
    "buildTool": "maven",
    "databaseType": "sql",
    "devDatabaseType": "h2Disk",
    "cacheProvider": "no",
    "enableHibernateCache": false,
    "enableSwaggerCodegen": false,
    "enableTranslation": true,
    "jhiPrefix": "jhi",
    "languages": [],
    "messageBroker": false,
    "prodDatabaseType": "mysql",
    "searchEngine": false,
    "testFrameworks": [],
    "websocket": false,
    "enableGradleEnterprise": false,
    "gradleEnterpriseHost": "",
    "applicationType": "gateway",
    "packageName": "com.yarolab.mytrackit",
    "packageFolder": "com/yarolab/mytrackit",
    "jhipsterVersion": "7.9.3",
    "clientPackageManager": "npm",
    "dtoSuffix": "DTO",
    "entitySuffix": "",
    "reactive": true,
    "clientTheme": "none",
    "clientThemeVariant": "",
    "applicationIndex": 0
  }
}
